setup.py
abakaffe/__init__.py
abakaffe/lib.py
abakaffe/script.py
abakaffe/version.py
abakaffe_cli.egg-info/PKG-INFO
abakaffe_cli.egg-info/SOURCES.txt
abakaffe_cli.egg-info/dependency_links.txt
abakaffe_cli.egg-info/entry_points.txt
abakaffe_cli.egg-info/requires.txt
abakaffe_cli.egg-info/top_level.txt