Metadata-Version: 1.0
Name: abakaffe-cli
Version: 0.2.8
Summary: A CLI for the Abakus Coffee API
Home-page: http://github.com/oyvindrobertsen/abakaffe-cli
Author: Øyvind Robertsen, Martin Hallén
Author-email: ['oyvindrobertsen@gmail.com', 'marthall@outlook.com']
License: MIT
Keywords: Abakus coffee API
Platform: UNKNOWN
